[{"roomID":"r102823","roomName":"n523","timetable":{"week":[{"day":"Monday","events":[]},{"day":"Tuesday","events":[{"event":"Cyber Security Short Course","start":"09:00","end":"17:00"}]},{"day":"Wednesday","events":[{"event":"Cyber Security Short Course","start":"09:00","end":"17:00"}]},{"day":"Thursday","events":[]},{"day":"Friday","events":[]},{"day":"Saturday","events":[]},{"day":"Sunday","events":[]}]}},{"roomID":"r102824","roomName":"n525","timetable":{"week":[{"day":"Monday","events":[]},{"day":"Tuesday","events":[]},{"day":"Wednesday","events":[]},{"day":"Thursday","events":[]},{"day":"Friday","events":[]},{"day":"Saturday","events":[]},{"day":"Sunday","events":[]}]}},{"roomID":"r102891","roomName":"n526","timetable":{"week":[{"day":"Monday","events":[]},{"day":"Tuesday","events":[]},{"day":"Wednesday","events":[]},{"day":"Thursday","events":[]},{"day":"Friday","events":[]},{"day":"Saturday","events":[]},{"day":"Sunday","events":[]}]}},{"roomID":"r102825","roomName":"n527","timetable":{"week":[{"day":"Monday","events":[]},{"day":"Tuesday","events":[]},{"day":"Wednesday","events":[]},{"day":"Thursday","events":[]},{"day":"Friday","events":[]},{"day":"Saturday","events":[]},{"day":"Sunday","events":[]}]}},{"roomID":"r102826","roomName":"n528","timetable":{"week":[{"day":"Monday","events":[]},{"day":"Tuesday","events":[]},{"day":"Wednesday","events":[]},{"day":"Thursday","events":[]},{"day":"Friday","events":[]},{"day":"Saturday","events":[]},{"day":"Sunday","events":[]}]}},{"roomID":"r102827","roomName":"n529","timetable":{"week":[{"day":"Monday","events":[]},{"day":"Tuesday","events":[]},{"day":"Wednesday","events":[]},{"day":"Thursday","events":[]},{"day":"Friday","events":[]},{"day":"Saturday","events":[]},{"day":"Sunday","events":[]}]}},{"roomID":"r102828","roomName":"n530","timetable":{"week":[{"day":"Monday","events":[]},{"day":"Tuesday","events":[]},{"day":"Wednesday","events":[]},{"day":"Thursday","events":[]},{"day":"Friday","events":[]},{"day":"Saturday","events":[]},{"day":"Sunday","events":[]}]}},{"roomID":"r102829","roomName":"n533","timetable":{"week":[{"day":"Monday","events":[]},{"day":"Tuesday","events":[]},{"day":"Wednesday","events":[]},{"day":"Thursday","events":[]},{"day":"Friday","events":[]},{"day":"Saturday","events":[]},{"day":"Sunday","events":[]}]}}]